dione/__init__.py
dione/_version.py
dione/cli.py
dione/gui.py
dione/utils.py
dione/assets/bootstrap.min.css
dione/cron/__init__.py
dione/cron/app.ini
dione/cron/config.py
dione/cron/db.py
dione/demos/demo.xlsx
dione/graph/__init__.py
dione/model/__init__.py
dione/model/tco.py
dione/model/cost_curve/__init__.py
dione/model/cost_curve/problem.py
dione/model/cross_opt/__init__.py
dione/model/cross_opt/problem.py
dione/rw/__init__.py
dione/rw/write.py
dione/rw/read/__init__.py
dione/rw/read/excel.py
dione/rw/read/parse.py
dione/templates/input_template.xlsx
dione/templates/input_template1.xlsx
dione-0.0.6.dist-info/AUTHORS.rst
dione-0.0.6.dist-info/LICENSE.txt
dione-0.0.6.dist-info/METADATA
dione-0.0.6.dist-info/WHEEL
dione-0.0.6.dist-info/entry_points.txt
dione-0.0.6.dist-info/top_level.txt
dione-0.0.6.dist-info/RECORD
